langchain_tool_server/__init__.py
langchain_tool_server/_version.py
langchain_tool_server/context.py
langchain_tool_server/mcp.py
langchain_tool_server/mcp_loader.py
langchain_tool_server/root.py
langchain_tool_server/splash.py
langchain_tool_server/tool.py
langchain_tool_server/tools.py
langchain_tool_server/auth/__init__.py
langchain_tool_server/auth/exceptions.py
langchain_tool_server/auth/middleware.py
langchain_tool_server/auth/types.py
langchain_tool_server-0.2.3.dist-info/METADATA
langchain_tool_server-0.2.3.dist-info/WHEEL
langchain_tool_server-0.2.3.dist-info/RECORD
