Metadata-Version: 2.4
Name: langchain-tool-server
Version: 0.2.3
Summary: LangChain Tool Server (Python)
Project-URL: repository, https://github.com/langchain-ai/langchain-tool-server
Requires-Python: >=3.10
Requires-Dist: fastapi>=0.110.0
Requires-Dist: langchain-auth>=0.1.2
Requires-Dist: mcp>=1.3.0
Requires-Dist: orjson>=3.10.15
Requires-Dist: pydantic>=2.7.2
Requires-Dist: structlog>=20.1.0
